_event_camera_drivers.cpython-39-x86_64-linux-gnu.so
event_camera_drivers/__init__.py
event_camera_drivers.libs/libelf-0-3d9de92a.176.so
event_camera_drivers.libs/libcaer-d340457a.so.3.3.15
event_camera_drivers.libs/libcap-79733b59.so.2.22
event_camera_drivers.libs/libusb-1-150b88da.0.so.0.1.0
event_camera_drivers.libs/libudev-1f672570.so.1.6.2
event_camera_drivers.libs/libbz2-a273e504.so.1.0.6
event_camera_drivers.libs/libdw-0-780627ce.176.so
event_camera_drivers.libs/liblzma-004595ca.so.5.2.2
event_camera_drivers.libs/libattr-4f2a9577.so.1.1.0
event_camera_drivers-0.2.0.dist-info/METADATA
event_camera_drivers-0.2.0.dist-info/RECORD
event_camera_drivers-0.2.0.dist-info/WHEEL
event_camera_drivers-0.2.0.dist-info/licenses/LICENSE
